akhdefo_functions/AkhdefoPlot.py
akhdefo_functions/Akhdefo_Classification.py
akhdefo_functions/Akhdefo_Coreg.py
akhdefo_functions/Akhdefo_GOI.py
akhdefo_functions/Akhdefo_TS.py
akhdefo_functions/Akhdefo_Tools.py
akhdefo_functions/Akhdefo_Utilities.py
akhdefo_functions/Filter_PreProc.py
akhdefo_functions/Mosaic_Crop.py
akhdefo_functions/OpticalFlow.py
akhdefo_functions/Stacked_Velocity.py
akhdefo_functions/Unzip_CopyFiles.py
akhdefo_functions/Video_Streamer.py
akhdefo_functions/__init__.py
akhdefo_functions/akhdefo_viewer.py
akhdefo_functions/backend.py
akhdefo_functions-2.5.72.dist-info/METADATA
akhdefo_functions-2.5.72.dist-info/WHEEL
akhdefo_functions-2.5.72.dist-info/top_level.txt
akhdefo_functions-2.5.72.dist-info/RECORD
