Metadata-Version: 2.1
Name: akhdefo_functions
Version: 2.5.72
Summary: Land Deformation Monitoring Using Optical and SAR Satellite Imagery
Home-page: https://github.com/mahmudsfu/AkhDefo
Author: Mahmud Mustafa Muhammad
Author-email: mahmud.muhamm1@gmail.com
License: Academic Free License (AFL)
Classifier: Development Status :: 3 - Alpha
Classifier: Intended Audience :: Science/Research
Classifier: License :: OSI Approved :: Academic Free License (AFL)
Classifier: Operating System :: Microsoft :: Windows :: Windows 10
Classifier: Operating System :: POSIX :: Linux
Classifier: Programming Language :: Python :: 3
Classifier: Programming Language :: Python :: 3.6
Classifier: Programming Language :: Python :: 3.7
Classifier: Programming Language :: Python :: 3.8
Classifier: Programming Language :: Python :: 3.9
Classifier: Programming Language :: Python :: 3.10
